sap_ecs_gcp_log_forwarder/__init__.py
sap_ecs_gcp_log_forwarder/config.py
sap_ecs_gcp_log_forwarder/log_processor.py
sap_ecs_gcp_log_forwarder/pub_sub_consumer.py
sap_ecs_gcp_log_forwarder-1.1.0.dist-info/LICENSE
sap_ecs_gcp_log_forwarder-1.1.0.dist-info/METADATA
sap_ecs_gcp_log_forwarder-1.1.0.dist-info/WHEEL
sap_ecs_gcp_log_forwarder-1.1.0.dist-info/entry_points.txt
sap_ecs_gcp_log_forwarder-1.1.0.dist-info/RECORD
