Metadata-Version: 2.1
Name: sap-ecs-gcp-log-forwarder
Version: 1.1.0
Summary: A package to consume events from an Google Pub/Sub, process log files, and forward them to a HTTP endpoint or file.
Home-page: https://www.sap.com/
License: SAP DEVELOPER LICENSE AGREEMENT
Keywords: SAP GCP Log Forwarder,SAP Log Forwarder
Author: SAP SE
Requires-Python: >=3.10,<4.0
Classifier: Development Status :: 5 - Production/Stable
Classifier: Intended Audience :: Developers
Classifier: License :: Other/Proprietary License
Classifier: Operating System :: MacOS :: MacOS X
Classifier: Operating System :: POSIX :: Linux
Classifier: Programming Language :: Python
Classifier: Programming Language :: Python :: 3
Classifier: Programming Language :: Python :: 3.10
Classifier: Programming Language :: Python :: 3.11
Classifier: Programming Language :: Python :: 3.12
Classifier: Topic :: Software Development :: Libraries :: Python Modules
Requires-Dist: cryptography (>=44.0.1,<45.0.0)
Requires-Dist: google-cloud-pubsub (>=2.21.2,<3.0.0)
Requires-Dist: google-cloud-storage (>=2.16.0,<3.0.0)
Requires-Dist: python-dotenv (>=1.0.1,<2.0.0)
Requires-Dist: requests (>=2.32.3,<3.0.0)
